{
	"info": {
		"_postman_id": "32377564-c710755e-fb25-4d84-ae05-267e4918b9b1",
		"name": "TestCollection",
		"schema": "https://schema.getpostman.com/json/collection/v2.1.0/collection.json"
	},
	"item": [
		{
			"name": "Test",
			"id": "32377564-8cd9c900-5346-48b5-81fb-3fec042025d8",
			"protocolProfileBehavior": {
				"disableBodyPruning": true
			},
			"request": {
				"method": "GET",
				"header": []
			},
			"response": []
		},
		{
			"name": "Test123",
			"id": "32377564-158057d1-462f-45d3-8d9f-8d71b62eafcf",
			"protocolProfileBehavior": {
				"disableBodyPruning": true
			},
			"request": {
				"method": "GET",
				"header": []
			},
			"response": []
		},
		{
			"name": "TestFinal",
			"id": "32377564-5355e681-4627-44fc-aa4d-bc787cc042e3",
			"protocolProfileBehavior": {
				"disableBodyPruning": true
			},
			"request": {
				"method": "GET",
				"header": []
			},
			"response": []
		}
	]
}